dmconvert/__init__.py
dmconvert/cli.py
dmconvert/convert.py
dmconvert/utils.py
dmconvert/guardgift/__init__.py
dmconvert/guardgift/gg_handler.py
dmconvert/guardgift/guard_and_gift.py
dmconvert/header/__init__.py
dmconvert/header/header.py
dmconvert/normal/__init__.py
dmconvert/normal/danmaku_array.py
dmconvert/normal/dytest.py
dmconvert/normal/normal_handler.py
dmconvert/superchat/__init__.py
dmconvert/superchat/superchat.py
dmconvert/superchat/superchat_handler.py
dmconvert-0.0.4.dist-info/METADATA
dmconvert-0.0.4.dist-info/WHEEL
dmconvert-0.0.4.dist-info/entry_points.txt
dmconvert-0.0.4.dist-info/licenses/LICENSE
dmconvert-0.0.4.dist-info/RECORD
