Metadata-Version: 2.4
Name: dmconvert
Version: 0.0.4
Summary: The Python toolkit package and cli designed for converting xml danmaku to ass.
Project-URL: Homepage, https://github.com/timerring/DanmakuConvert
Author: timerring
License: MIT License
License-File: LICENSE
Classifier: License :: OSI Approved :: MIT License
Classifier: Operating System :: OS Independent
Classifier: Programming Language :: Python :: 3
Requires-Python: >=3.6
